LICENSE.txt
MANIFEST.in
README.md
setup.py
src/ISAMBARD.egg-info/PKG-INFO
src/ISAMBARD.egg-info/SOURCES.txt
src/ISAMBARD.egg-info/dependency_links.txt
src/ISAMBARD.egg-info/not-zip-safe
src/ISAMBARD.egg-info/requires.txt
src/ISAMBARD.egg-info/top_level.txt
src/isambard/__init__.py
src/isambard/__pycache__/__init__.cpython-37.pyc
src/isambard/evaluation/__init__.py
src/isambard/evaluation/contact_order.py
src/isambard/evaluation/dssp.py
src/isambard/evaluation/hydrophobic_fitness.py
src/isambard/evaluation/pacc.py
src/isambard/evaluation/packing_density.py
src/isambard/evaluation/__pycache__/__init__.cpython-37.pyc
src/isambard/evaluation/__pycache__/contact_order.cpython-37.pyc
src/isambard/evaluation/__pycache__/dssp.cpython-37.pyc
src/isambard/evaluation/__pycache__/hydrophobic_fitness.cpython-37.pyc
src/isambard/evaluation/__pycache__/pacc.cpython-37.pyc
src/isambard/evaluation/__pycache__/packing_density.cpython-37.pyc
src/isambard/modelling/__init__.py
src/isambard/modelling/non_canonical.py
src/isambard/modelling/scwrl.py
src/isambard/modelling/__pycache__/__init__.cpython-37.pyc
src/isambard/modelling/__pycache__/create_loop_database.cpython-37.pyc
src/isambard/modelling/__pycache__/extract_loop_data.cpython-37.pyc
src/isambard/modelling/__pycache__/non_canonical.cpython-37.pyc
src/isambard/modelling/__pycache__/scwrl.cpython-37.pyc
src/isambard/modelling/reference_ampals/README.md
src/isambard/modelling/reference_ampals/non_canonical_amino_acids/hydroxyproline_ref_1bkv_0_6.pickle
src/isambard/optimisation/__init__.py
src/isambard/optimisation/base_evo_opt.py
src/isambard/optimisation/evo_optimizers.py
src/isambard/optimisation/mmc_optimizer.py
src/isambard/specifications/__init__.py
src/isambard/specifications/coiledcoil.py
src/isambard/specifications/helix.py
src/isambard/specifications/nucleic_acid_duplex.py
src/isambard/specifications/nucleic_acid_strand.py
src/isambard/specifications/solenoid.py
src/isambard/specifications/ta_polypeptide.c
src/isambard/specifications/ta_polypeptide.cpython-37m-x86_64-linux-gnu.so
src/isambard/specifications/ta_polypeptide.pyx