Metadata-Version: 2.1
Name: ISAMBARD
Version: 2.3.1
Summary: A package for biomolecular analysis, modelling and design
Home-page: https://github.com/isambard-uob/isambard
Author: Woolfson Group, University of Bristol
Author-email: chris.wood@ed.ac.uk
License: UNKNOWN
Platform: UNKNOWN
Classifier: Intended Audience :: Science/Research
Classifier: License :: OSI Approved :: MIT License
Classifier: Natural Language :: English
Classifier: Topic :: Scientific/Engineering :: Bio-Informatics
Classifier: Programming Language :: Python :: 3.5
Classifier: Programming Language :: Python :: 3.6
